molass_data/__init__.py
molass_data/SAMPLE1/PREFIX1_00000.dat
molass_data/SAMPLE1/PREFIX1_00001.dat
molass_data/SAMPLE1/PREFIX1_00002.dat
molass_data/SAMPLE1/PREFIX1_00003.dat
molass_data/SAMPLE1/PREFIX1_00004.dat
molass_data/SAMPLE1/PREFIX1_00005.dat
molass_data/SAMPLE1/PREFIX1_00006.dat
molass_data/SAMPLE1/PREFIX1_00007.dat
molass_data/SAMPLE1/PREFIX1_00008.dat
molass_data/SAMPLE1/PREFIX1_00009.dat
molass_data/SAMPLE1/PREFIX1_00010.dat
molass_data/SAMPLE1/PREFIX1_00011.dat
molass_data/SAMPLE1/PREFIX1_00012.dat
molass_data/SAMPLE1/PREFIX1_00013.dat
molass_data/SAMPLE1/PREFIX1_00014.dat
molass_data/SAMPLE1/PREFIX1_00015.dat
molass_data/SAMPLE1/PREFIX1_00016.dat
molass_data/SAMPLE1/PREFIX1_00017.dat
molass_data/SAMPLE1/PREFIX1_00018.dat
molass_data/SAMPLE1/PREFIX1_00019.dat
molass_data/SAMPLE1/PREFIX1_00020.dat
molass_data/SAMPLE1/PREFIX1_00021.dat
molass_data/SAMPLE1/PREFIX1_00022.dat
molass_data/SAMPLE1/PREFIX1_00023.dat
molass_data/SAMPLE1/PREFIX1_00024.dat
molass_data/SAMPLE1/PREFIX1_00025.dat
molass_data/SAMPLE1/PREFIX1_00026.dat
molass_data/SAMPLE1/PREFIX1_00027.dat
molass_data/SAMPLE1/PREFIX1_00028.dat
molass_data/SAMPLE1/PREFIX1_00029.dat
molass_data/SAMPLE1/PREFIX1_00030.dat
molass_data/SAMPLE1/PREFIX1_00031.dat
molass_data/SAMPLE1/PREFIX1_00032.dat
molass_data/SAMPLE1/PREFIX1_00033.dat
molass_data/SAMPLE1/PREFIX1_00034.dat
molass_data/SAMPLE1/PREFIX1_00035.dat
molass_data/SAMPLE1/PREFIX1_00036.dat
molass_data/SAMPLE1/PREFIX1_00037.dat
molass_data/SAMPLE1/PREFIX1_00038.dat
molass_data/SAMPLE1/PREFIX1_00039.dat
molass_data/SAMPLE1/PREFIX1_00040.dat
molass_data/SAMPLE1/PREFIX1_00041.dat
molass_data/SAMPLE1/PREFIX1_00042.dat
molass_data/SAMPLE1/PREFIX1_00043.dat
molass_data/SAMPLE1/PREFIX1_00044.dat
molass_data/SAMPLE1/PREFIX1_00045.dat
molass_data/SAMPLE1/PREFIX1_00046.dat
molass_data/SAMPLE1/PREFIX1_00047.dat
molass_data/SAMPLE1/PREFIX1_00048.dat
molass_data/SAMPLE1/PREFIX1_00049.dat
molass_data/SAMPLE1/PREFIX1_00050.dat
molass_data/SAMPLE1/PREFIX1_00051.dat
molass_data-0.3.0.dist-info/METADATA
molass_data-0.3.0.dist-info/WHEEL
molass_data-0.3.0.dist-info/licenses/LICENSE.txt
molass_data-0.3.0.dist-info/RECORD
